textual_dissect/__init__.py
textual_dissect/__main__.py
textual_dissect/app.py
textual_dissect-0.2.0.dist-info/licenses/LICENSE
textual_dissect-0.2.0.dist-info/METADATA
textual_dissect-0.2.0.dist-info/WHEEL
textual_dissect-0.2.0.dist-info/entry_points.txt
textual_dissect-0.2.0.dist-info/top_level.txt
textual_dissect-0.2.0.dist-info/RECORD
