Metadata-Version: 2.4
Name: textual-dissect
Version: 0.2.0
Summary: A tool for dissecting Textual widgets, including default CSS and more
Author: TomJGooding
License-Expression: GPL-3.0-or-later
Project-URL: Homepage, https://github.com/TomJGooding/textual-dissect
Classifier: Development Status :: 4 - Beta
Classifier: Environment :: Console
Classifier: Intended Audience :: Developers
Classifier: Programming Language :: Python :: 3.9
Classifier: Programming Language :: Python :: 3.10
Classifier: Programming Language :: Python :: 3.11
Classifier: Programming Language :: Python :: 3.12
Classifier: Programming Language :: Python :: 3.13
Requires-Python: >=3.9
License-File: LICENSE
Requires-Dist: textual>=5.0.0
Requires-Dist: tree-sitter>=0.25.0
Requires-Dist: tree-sitter-scss>=1.0.0
Provides-Extra: dev
Requires-Dist: black; extra == "dev"
Requires-Dist: flake8; extra == "dev"
Requires-Dist: isort; extra == "dev"
Requires-Dist: mypy; extra == "dev"
Requires-Dist: textual-dev; extra == "dev"
Dynamic: license-file
